bytedbothelper/__init__.py
bytedbothelper-0.0.1.dist-info/METADATA
bytedbothelper-0.0.1.dist-info/WHEEL
bytedbothelper-0.0.1.dist-info/top_level.txt
bytedbothelper-0.0.1.dist-info/RECORD
